tracllm/__init__.py
tracllm/evaluate.py
tracllm/load_dataset.py
tracllm/prompts.py
tracllm/utils.py
tracllm/attribution/__init__.py
tracllm/attribution/attribute.py
tracllm/attribution/perturbation_based.py
tracllm/attribution/self_citation.py
tracllm/models/GPT.py
tracllm/models/HF_model.py
tracllm/models/Llama.py
tracllm/models/Model.py
tracllm/models/__init__.py
tracllm-0.1.6.dist-info/METADATA
tracllm-0.1.6.dist-info/WHEEL
tracllm-0.1.6.dist-info/top_level.txt
tracllm-0.1.6.dist-info/RECORD
